nputop/__init__.py
nputop/main.py
nputop-0.0.3.dist-info/LICENSE
nputop-0.0.3.dist-info/METADATA
nputop-0.0.3.dist-info/WHEEL
nputop-0.0.3.dist-info/entry_points.txt
nputop-0.0.3.dist-info/top_level.txt
nputop-0.0.3.dist-info/RECORD
