Metadata-Version: 2.1
Name: nputop
Version: 0.0.3
Summary: NPU monitoring tool with TUI interface
Home-page: https://github.com/Rvelamen/nputop
Author: Rvelamen
Author-email: your.email@example.com
License-File: LICENSE
Requires-Dist: textual
Requires-Dist: psutil
Requires-Dist: rich
